README.md
setup.cfg
setup.py
convolut/__init__.py
convolut/epoch.py
convolut/events.py
convolut/loader.py
convolut/runner.py
convolut/settings.py
convolut.egg-info/PKG-INFO
convolut.egg-info/SOURCES.txt
convolut.egg-info/dependency_links.txt
convolut.egg-info/not-zip-safe
convolut.egg-info/requires.txt
convolut.egg-info/top_level.txt
convolut/constants/__init__.py
convolut/constants/ansi_color.py
convolut/constants/console_mode.py
convolut/constants/flush_type.py
convolut/constants/loader_name.py
convolut/constants/schedule_type.py
convolut/constants/state_mode.py
convolut/criterion/__init__.py
convolut/criterion/bce_dice.py
convolut/criterion/dice.py
convolut/logger/__init__.py
convolut/logger/console.py
convolut/logger/file.py
convolut/metric/__init__.py
convolut/metric/dice.py
convolut/metric/events.py
convolut/metric/loss.py
convolut/metric/metric_manager.py
convolut/model/__init__.py
convolut/model/events.py
convolut/model/infer_manager.py
convolut/model/model_manager.py
convolut/state/__init__.py
convolut/state/events.py
convolut/state/file_checkpoint.py
convolut/state/state_manager.py
convolut/trigger/__init__.py
convolut/trigger/early_stopper.py
convolut/utils/__init__.py
convolut/utils/dice.py
convolut/utils/loader.py