Metadata-Version: 2.1
Name: convolut
Version: 0.0.4
Summary: Distributed development and modularity for deep learning
Home-page: https://github.com/convolut/convolut
Author: Andrey Avdeev
Author-email: seorazer@gmail.com
License: Apache 2.0
Keywords: convolut modularity decoupled dl
Platform: UNKNOWN
Requires-Python: >=3.7
